fbbot/__init__.py
fbbot/_version.py
fbbot/bot.py
fbbot/element.py
fbbot/templates.py
fbbot/wrappers.py
fbbot/test/__init__.py
fbbot/test/bot_example.py
fbbot/test/simpleEchoBot.orig.py
fbbot/test/simpleEchoBot.py
fbbot-1.0.10.dist-info/DESCRIPTION.rst
fbbot-1.0.10.dist-info/METADATA
fbbot-1.0.10.dist-info/RECORD
fbbot-1.0.10.dist-info/WHEEL
fbbot-1.0.10.dist-info/metadata.json
fbbot-1.0.10.dist-info/top_level.txt
