Metadata-Version: 2.0
Name: fbbot
Version: 1.0.10
Summary: fbbot is a sim1ple bot class to showcasing the Facebook Messenger Platform
Home-page: https://github.com/espacioAntonio/fbbot
Author: espacioAntonio
Author-email: espacio.antonio@gmail.com
License: MIT License
Platform: UNKNOWN
Classifier: Development Status :: 4 - Beta
Classifier: Intended Audience :: Developers
Classifier: License :: OSI Approved :: MIT License
Classifier: Operating System :: OS Independent
Classifier: Programming Language :: Python
Classifier: Programming Language :: Python :: 3
Classifier: Programming Language :: Python :: 3.4
Classifier: Programming Language :: Python :: 3.5
Classifier: Development Status :: 3 - Alpha
Classifier: Topic :: Communications :: Chat
Classifier: Topic :: Internet :: WWW/HTTP
Requires-Dist: requests (==2.13.0)
